pycose/__init__.py
pycose/algorithms.py
pycose/exceptions.py
pycose/headers.py
pycose/py.typed
pycose/utils.py
pycose/extensions/__init__.py
pycose/extensions/x509.py
pycose/keys/__init__.py
pycose/keys/cosekey.py
pycose/keys/curves.py
pycose/keys/ec2.py
pycose/keys/keyops.py
pycose/keys/keyparam.py
pycose/keys/keytype.py
pycose/keys/okp.py
pycose/keys/rsa.py
pycose/keys/symmetric.py
pycose/messages/__init__.py
pycose/messages/context.py
pycose/messages/cosebase.py
pycose/messages/cosemessage.py
pycose/messages/enc0message.py
pycose/messages/enccommon.py
pycose/messages/encmessage.py
pycose/messages/mac0message.py
pycose/messages/maccommon.py
pycose/messages/macmessage.py
pycose/messages/recipient.py
pycose/messages/sign1message.py
pycose/messages/signcommon.py
pycose/messages/signer.py
pycose/messages/signmessage.py
pycose-1.1.0.dist-info/LICENSE
pycose-1.1.0.dist-info/METADATA
pycose-1.1.0.dist-info/WHEEL
pycose-1.1.0.dist-info/top_level.txt
pycose-1.1.0.dist-info/RECORD
