Metadata-Version: 2.1
Name: pycose
Version: 1.1.0
Summary: CBOR Object Signing and Encryption (COSE) implementation
Home-page: https://github.com/TimothyClaeys/pycose
Author: Timothy Claeys
Author-email: timothy.claeys@gmail.com
License: BSD 3-Clause License
Project-URL: Documentation, https://pycose.readthedocs.io/en/latest/
Project-URL: Source, https://github.com/TimothyClaeys/pycose
Project-URL: Download, https://pypi.org/project/pycose/
Keywords: 'COSE','Internet of Things','CBOR','object security','EDHOC','OSCORE','cryptography'
Platform: any
Classifier: Development Status :: 5 - Production/Stable
Classifier: Intended Audience :: Developers
Classifier: Topic :: Internet
Classifier: Topic :: Communications
Classifier: Topic :: Software Development
Classifier: Topic :: System :: Networking
Classifier: License :: OSI Approved :: BSD License
Classifier: Programming Language :: Python :: 3
Classifier: Programming Language :: Python :: 3.7
Classifier: Programming Language :: Python :: 3.8
Classifier: Programming Language :: Python :: 3.9
Classifier: Programming Language :: Python :: 3.10
Requires-Python: >=3.7
License-File: LICENSE
Requires-Dist: cryptography
Requires-Dist: cbor2
Requires-Dist: ecdsa
Requires-Dist: attrs
Requires-Dist: certvalidator
Provides-Extra: develop
Requires-Dist: cryptography; extra == "develop"
Requires-Dist: cbor2; extra == "develop"
Requires-Dist: ecdsa; extra == "develop"
Requires-Dist: attrs; extra == "develop"
Requires-Dist: certvalidator; extra == "develop"
Requires-Dist: pytest>=6.0.1; extra == "develop"
Requires-Dist: mypy>=0.782; extra == "develop"
Requires-Dist: coverage>=5.2.1; extra == "develop"
Requires-Dist: flake8>=3.8.3; extra == "develop"
Requires-Dist: pep8-naming>=0.11.1; extra == "develop"
Requires-Dist: Sphinx>=3.3.1; extra == "develop"
Requires-Dist: sphinx_rtd_theme>=0.5.0; extra == "develop"
Requires-Dist: sphinxemoji; extra == "develop"
